MANIFEST.in
README.md
setup.py
django_markup_mixin.egg-info/PKG-INFO
django_markup_mixin.egg-info/SOURCES.txt
django_markup_mixin.egg-info/dependency_links.txt
django_markup_mixin.egg-info/top_level.txt
django_markup_mixin.egg-info/zip-safe
markup_mixin/__init__.py
markup_mixin/models.py
markup_mixin/urls.py
markup_mixin/views.py