Metadata-Version: 1.0
Name: django-markup-mixin
Version: 0.1.0
Summary: Add pre-rendered markup fields to your django models with the least work.
Home-page: http://github.com/powellc/django-markup-mixin
Author: Colin Powell
Author-email: colin@onecardinal.com
License: BSD
Download-URL: http://github.com/powellc/django-markup-mixin/downloads
Platform: UNKNOWN
Classifier: Development Status :: 4 - Beta
Classifier: Environment :: Web Environment
Classifier: Intended Audience :: Developers
Classifier: License :: OSI Approved :: BSD License
Classifier: Operating System :: OS Independent
Classifier: Programming Language :: Python
Classifier: Framework :: Django
